starlog_mcp/__init__.py
starlog_mcp/debug_diary.py
starlog_mcp/hpi_system.py
starlog_mcp/models.py
starlog_mcp/models_old.py
starlog_mcp/models_v2.py
starlog_mcp/rules.py
starlog_mcp/rules_brain_integration.py
starlog_mcp/starlog.py
starlog_mcp/starlog_mcp.py
starlog_mcp/starlog_sessions.py
starlog_mcp-0.1.68.dist-info/METADATA
starlog_mcp-0.1.68.dist-info/WHEEL
starlog_mcp-0.1.68.dist-info/entry_points.txt
starlog_mcp-0.1.68.dist-info/top_level.txt
starlog_mcp-0.1.68.dist-info/RECORD
