Metadata-Version: 2.4
Name: starlog-mcp
Version: 0.1.68
Summary: STARLOG documentation workflow MCP for Claude Code integration
Home-page: https://github.com/anthropics/claude-code
Author: Isaac and Claude
Author-email: Isaac and Claude <noreply@anthropic.com>
License: MIT
Project-URL: Homepage, https://github.com/sancovp/starlog-mcp
Project-URL: Repository, https://github.com/sancovp/starlog-mcp
Project-URL: Issues, https://github.com/sancovp/starlog-mcp/issues
Keywords: mcp,documentation,workflow,starlog,claude-code
Classifier: Development Status :: 3 - Alpha
Classifier: Intended Audience :: Developers
Classifier: License :: OSI Approved :: MIT License
Classifier: Programming Language :: Python :: 3
Classifier: Programming Language :: Python :: 3.8
Classifier: Programming Language :: Python :: 3.9
Classifier: Programming Language :: Python :: 3.10
Classifier: Programming Language :: Python :: 3.11
Classifier: Topic :: Software Development :: Documentation
Classifier: Topic :: Text Processing :: Markup
Requires-Python: >=3.8
Requires-Dist: fastmcp>=2.0.0
Requires-Dist: pydantic>=2.0.0
Requires-Dist: heaven-framework>=0.1.13
Provides-Extra: dev
Requires-Dist: pytest; extra == "dev"
Requires-Dist: pytest-asyncio; extra == "dev"
Requires-Dist: mcp-use; extra == "dev"
Dynamic: author
Dynamic: home-page
Dynamic: requires-python
